free_llms/__init__.py
free_llms/callbacks.py
free_llms/constants.py
free_llms/langchain_model.py
free_llms/models.py
free_llms/utils.py
free_llms-0.1.3.1.dist-info/LICENSE
free_llms-0.1.3.1.dist-info/METADATA
free_llms-0.1.3.1.dist-info/WHEEL
free_llms-0.1.3.1.dist-info/RECORD
