Metadata-Version: 2.1
Name: free-llms
Version: 0.1.3.1
Summary: Use LLMs for Free.
License: MIT
Author: keenborder786
Author-email: 21110290@lums.edu.pk
Requires-Python: >=3.9,<4.0
Classifier: License :: OSI Approved :: MIT License
Classifier: Programming Language :: Python :: 3
Classifier: Programming Language :: Python :: 3.9
Classifier: Programming Language :: Python :: 3.10
Classifier: Programming Language :: Python :: 3.11
Classifier: Programming Language :: Python :: 3.12
Requires-Dist: beautifulsoup4 (>=4.12.3,<5.0.0)
Requires-Dist: fake-useragent (>=1.5.1,<2.0.0)
Requires-Dist: langchain (>=0.2.1,<0.3.0)
Requires-Dist: langchain-community (>=0.2.3,<0.3.0)
Requires-Dist: pydantic (>=2.7.3,<3.0.0)
Requires-Dist: selenium (>=4.21.0,<5.0.0)
Requires-Dist: undetected-chromedriver (>=3.5.5,<4.0.0)
